mesh_air_quality/__init__.py
mesh_air_quality/defaults.py
mesh_air_quality/main.py
mesh_air_quality/lib/__init__.py
mesh_air_quality/lib/air_quality_pb2.py
mesh_air_quality-0.0.6.dist-info/LICENSE
mesh_air_quality-0.0.6.dist-info/METADATA
mesh_air_quality-0.0.6.dist-info/WHEEL
mesh_air_quality-0.0.6.dist-info/top_level.txt
mesh_air_quality-0.0.6.dist-info/RECORD
