Metadata-Version: 2.1
Name: mesh-air-quality
Version: 0.0.6
Summary: Air Quality client for mesh-pravah
Home-page: https://github.com/pravahio
Author: Abhishek Upperwal
Author-email: mesh@soket.in
License: UNKNOWN
Platform: UNKNOWN
Classifier: Programming Language :: Python :: 3
Classifier: License :: OSI Approved :: MIT License
Classifier: Operating System :: OS Independent
Requires-Dist: mesh-rpc
Requires-Dist: dict-to-protobuf
